accoladepraccli-2.5.data/scripts/accolade
accoladepraccli-2.5.data/scripts/sa.py
accoladepraccli-2.5.dist-info/METADATA
accoladepraccli-2.5.dist-info/RECORD
accoladepraccli-2.5.dist-info/WHEEL
accoladepraccli-2.5.dist-info/top_level.txt
cliparser/__init__.py
cliparser/argparser.py
cliparser/os.py
cliparser/play.py
cliparser/sa.py
parser/__init__.py
parser/argparser.py
parser/os.py
parser/play.py
parser/sa.py
