Metadata-Version: 2.1
Name: accoladepraccli
Version: 2.5
Summary: Accolade CLI
Home-page: UNKNOWN
Author: J.V.
Author-email: UNKNOWN
License: UNKNOWN
Platform: UNKNOWN
Requires-Dist: boto3
